micropython_tmp117/__init__.py
micropython_tmp117/i2c_helpers.py
micropython_tmp117/tmp117.py
micropython_tmp117-0.2.2.dist-info/LICENSE
micropython_tmp117-0.2.2.dist-info/METADATA
micropython_tmp117-0.2.2.dist-info/WHEEL
micropython_tmp117-0.2.2.dist-info/top_level.txt
micropython_tmp117-0.2.2.dist-info/RECORD
