Metadata-Version: 2.1
Name: micropython-tmp117
Version: 0.2.2
Summary: MicroPython Driver for the TMP117 temperature sensor
Author-email: "Jose D. Montoya" <tmp117@mailmeto.mozmail.com>
License: MIT
Project-URL: Homepage, https://github.com/jposada202020/micropython_TMP117
Keywords: micropython,tmp117,temperature,sensor
Classifier: Intended Audience :: Developers
Classifier: Topic :: Software Development :: Libraries
Classifier: Topic :: Software Development :: Embedded Systems
Classifier: Topic :: System :: Hardware
Classifier: License :: OSI Approved :: MIT License
Classifier: Programming Language :: Python :: Implementation :: MicroPython
License-File: LICENSE
